{
    "tenantId":  "cg.mungeli",
    "moduleName":  "egov-location",
    "TenantBoundary":  [
                           {
                               "hierarchyType":  {
                                                     "code":  "REVENUE",
                                                     "name":  "REVENUE"
                                                 },
                               "boundary":  {
                                                "id":  1,
                                                "boundaryNum":  1,
                                                "name":  "Mungeli",
                                                "localname":  "Mungeli",
                                                "longitude":  null,
                                                "latitude":  null,
                                                "label":  "City",
                                                "code":  "cg.mungeli",
                                                "children":  [
                                                                 {
                                                                     "id":  "8cc217b8-b89a-465e-b0a5-388d336c48f9",
                                                                     "boundaryNum":  1,
                                                                     "name":  "Ward 1",
                                                                     "localname":  "Ward 1",
                                                                     "longitude":  null,
                                                                     "latitude":  null,
                                                                     "label":  "Ward",
                                                                     "code":  "MUNG_W1",
                                                                     "children":  [

                                                                                  ]
                                                                 }
                                                             ]
                                            }
                           }
                       ]
}